env/bin/jp.py
libdev/__init__.py
libdev/cfg.py
libdev/check.py
libdev/codes.py
libdev/crypt.py
libdev/dev.py
libdev/doc.py
libdev/fin.py
libdev/gen.py
libdev/img.py
libdev/lang.py
libdev/log.py
libdev/num.py
libdev/req.py
libdev/s3.py
libdev/time.py
libdev-0.101.dist-info/licenses/LICENSE
libdev-0.101.dist-info/METADATA
libdev-0.101.dist-info/WHEEL
libdev-0.101.dist-info/top_level.txt
libdev-0.101.dist-info/RECORD
