Metadata-Version: 2.4
Name: libdev
Version: 0.101
Summary: Set of standard functions for development
Home-page: https://github.com/chilleco/lib
Author: Alex Poloz
Author-email: Alex Poloz <alexypoloz@gmail.com>
License: MIT License
Project-URL: Source, https://github.com/chilleco/lib
Keywords: standard,lib,dev,development,cfg,config,generate,codes,tokens,ids,passwords,generator,ciphers,time,formatter,nlp,natural language,aws,s3,upload file,file server
Classifier: Development Status :: 4 - Beta
Classifier: Environment :: Console
Classifier: Intended Audience :: Developers
Classifier: Topic :: Software Development :: Libraries :: Application Frameworks
Classifier: License :: OSI Approved :: MIT License
Classifier: Programming Language :: Python :: 3
Classifier: Programming Language :: Python :: 3 :: Only
Classifier: Programming Language :: Python :: 3.10
Classifier: Programming Language :: Python :: 3.11
Classifier: Programming Language :: Python :: 3.12
Classifier: Programming Language :: Python :: 3.13
Classifier: Operating System :: OS Independent
Requires-Python: >=3.10, <4
License-File: LICENSE
Requires-Dist: aiohttp>=3.13.2
Requires-Dist: python-dotenv>=1.2.1
Requires-Dist: boto3>=1.42.0
Requires-Dist: Pillow>=12.0.0
Requires-Dist: pillow-heif>=1.0.0
Requires-Dist: loguru>=0.7.3
Provides-Extra: dev
Requires-Dist: build>=1.3.0; extra == "dev"
Requires-Dist: setuptools>=80.9.0; extra == "dev"
Requires-Dist: twine>=6.2.0; extra == "dev"
Requires-Dist: pylint>=4.0.4; extra == "dev"
Requires-Dist: pytest>=9.0.1; extra == "dev"
Requires-Dist: pytest-asyncio>=1.3.0; extra == "dev"
Dynamic: author
Dynamic: home-page
Dynamic: license-file
Dynamic: requires-python
